filequery/__init__.py
filequery/__main__.py
filequery/exceptions.py
filequery/file_query_args.py
filequery/filedb.py
filequery/filetype.py
filequery/queryresult.py
filequery/tui/duckui.py
filequery/tui/help_content.py
filequery/tui/screens/file_browser.py
filequery/tui/screens/menu.py
filequery/tui/screens/menu_events.py
filequery/tui/styles/style.tcss
filequery-0.2.6.dist-info/LICENSE
filequery-0.2.6.dist-info/METADATA
filequery-0.2.6.dist-info/WHEEL
filequery-0.2.6.dist-info/entry_points.txt
filequery-0.2.6.dist-info/top_level.txt
filequery-0.2.6.dist-info/RECORD
