Metadata-Version: 2.1
Name: filequery
Version: 0.2.6
Summary: Query CSV and Parquet files using SQL
Author-email: Markus Hutnik <markus@markushutnik.com>
License: MIT
Project-URL: repository, https://github.com/MarkyMan4/filequery
Classifier: Programming Language :: Python :: 3
Requires-Python: >=3.8
License-File: LICENSE
Requires-Dist: duckdb ==0.10.1
Requires-Dist: importlib-metadata ==6.8.0
Requires-Dist: linkify-it-py ==2.0.2
Requires-Dist: markdown-it-py ==3.0.0
Requires-Dist: mdit-py-plugins ==0.4.0
Requires-Dist: mdurl ==0.1.2
Requires-Dist: numpy ==1.26.1
Requires-Dist: Pygments ==2.16.1
Requires-Dist: rich ==13.6.0
Requires-Dist: textual ==0.47.1
Requires-Dist: tree-sitter ==0.20.2
Requires-Dist: tree-sitter-languages ==1.8.0
Requires-Dist: typing-extensions ==4.8.0
Requires-Dist: uc-micro-py ==1.0.2
Requires-Dist: zipp ==3.17.0
